LICENSE
MANIFEST.in
README.md
pypelogs.py
setup.py
g11pyutils/Connector.py
g11pyutils/IndexedDictList.py
g11pyutils/StopWatch.py
g11pyutils/__init__.py
g11pyutils/test/__init__.py
g11pyutils/test/test_IndexedDictList.py
pypef/__init__.py
pypef/bucket.py
pypef/each.py
pypef/eval.py
pypef/exec_filter.py
pypef/feed.py
pypef/filter.py
pypef/groupby.py
pypef/head.py
pypef/keep.py
pypef/log.py
pypef/set.py
pypef/sort.py
pypef/split.py
pypef/tail.py
pypef/trim.py
pypef/test/__init__.py
pypef/test/test_tail.py
pypein/__init__.py
pypein/csv_in.py
pypein/flickr.py
pypein/http.py
pypein/instagram_in.py
pypein/json_in.py
pypein/mongodb.py
pypein/mysql_in.py
pypein/nginx.py
pypein/oracle.py
pypein/postgresql.py
pypein/text.py
pypein/twitter.py
pypein/wikip.py
pypelogs.egg-info/PKG-INFO
pypelogs.egg-info/SOURCES.txt
pypelogs.egg-info/dependency_links.txt
pypelogs.egg-info/entry_points.txt
pypelogs.egg-info/requires.txt
pypelogs.egg-info/top_level.txt
pypeout/__init__.py
pypeout/csv_out.py
pypeout/http.py
pypeout/json_out.py
pypeout/mongodb.py
pypeout/mysql_out.py
pypeout/sql_out.py
pypeout/text_out.py