Metadata-Version: 1.0
Name: pypelogs
Version: 0.3.13
Summary: A generator-based tool for piping log data (and other sources) from inputs to outputs, with any number of filters in between.
Home-page: https://github.com/gear11/pypelogs
Author: Andy Jenkins
Author-email: andy@gear11.com
License: GPL3
Platform: UNKNOWN
